vedro_gitlab_reporter/__init__.py
vedro_gitlab_reporter/_collapsable_mode.py
vedro_gitlab_reporter/_gitlab_reporter.py
vedro_gitlab_reporter/py.typed
vedro_gitlab_reporter-2.1.4.dist-info/LICENSE
vedro_gitlab_reporter-2.1.4.dist-info/METADATA
vedro_gitlab_reporter-2.1.4.dist-info/WHEEL
vedro_gitlab_reporter-2.1.4.dist-info/top_level.txt
vedro_gitlab_reporter-2.1.4.dist-info/RECORD
