Metadata-Version: 2.1
Name: vedro-gitlab-reporter
Version: 2.1.4
Summary: GitLab reporter with collapsable sections for Vedro framework
Home-page: https://github.com/vedro-universe/vedro-gitlab-reporter
Author: Nikita Tsvetkov
Author-email: tsv1@fastmail.com
License: Apache-2.0
Project-URL: Docs, https://vedro.io/docs/integrations/gitlab-reporter
Project-URL: GitHub, https://github.com/vedro-universe/vedro-gitlab-reporter
Classifier: License :: OSI Approved :: Apache Software License
Classifier: Programming Language :: Python :: 3.7
Classifier: Programming Language :: Python :: 3.8
Classifier: Programming Language :: Python :: 3.9
Classifier: Programming Language :: Python :: 3.10
Classifier: Programming Language :: Python :: 3.11
Classifier: Typing :: Typed
Requires-Python: >=3.7
License-File: LICENSE
Requires-Dist: vedro <2.0,>=1.7
